PyResScale/__init__.py
PyResScale-1.0.0.dist-info/LICENSE.txt
PyResScale-1.0.0.dist-info/METADATA
PyResScale-1.0.0.dist-info/WHEEL
PyResScale-1.0.0.dist-info/top_level.txt
PyResScale-1.0.0.dist-info/RECORD
